anyfile/__init__.py
anyfile/_types.py
anyfile/main.py
anyfile/open.py
anyfile/version.py
anyfile/formats/__init__.py
anyfile-0.0.1.dist-info/METADATA
anyfile-0.0.1.dist-info/WHEEL
anyfile-0.0.1.dist-info/top_level.txt
anyfile-0.0.1.dist-info/RECORD
